AUTHORS
CHANGELOG.txt
DESCRIPTION
LICENSE
MANIFEST.in
README.rst
setup.cfg
setup.py
cmsplugin_django_outlets.egg-info/PKG-INFO
cmsplugin_django_outlets.egg-info/SOURCES.txt
cmsplugin_django_outlets.egg-info/dependency_links.txt
cmsplugin_django_outlets.egg-info/requires.txt
cmsplugin_django_outlets.egg-info/top_level.txt
cmsplugin_outlets/__init__.py
cmsplugin_outlets/cms_app.py
cmsplugin_outlets/menu.py
cmsplugin_outlets/models.py
cmsplugin_outlets/tests/__init__.py
cmsplugin_outlets/tests/settings.py
cmsplugin_outlets/tests/test_settings.py
cmsplugin_outlets/tests/urls.py
cmsplugin_outlets/tests/templates/base.html