Metadata-Version: 1.0
Name: cmsplugin-django-outlets
Version: 0.2
Summary: Provides django-cms integration for django-outlets
